semiolog/.DS_Store
semiolog/__init__.py
semiolog/cenematic.py
semiolog/config.py
semiolog/corpus.py
semiolog/functive.py
semiolog/paths.py
semiolog/temp.py
semiolog/text.py
semiolog/util.py
semiolog/util_slg.py
semiolog/vocabulary.py
semiolog/classifier/__init__.py
semiolog/classifier/pclass.py
semiolog/paradigmatic/.DS_Store
semiolog/paradigmatic/__init__.py
semiolog/paradigmatic/paradigm.py
semiolog/syntagmatic/.DS_Store
semiolog/syntagmatic/__init__.py
semiolog/syntagmatic/__init__old.py
semiolog/syntagmatic/chain.py
semiolog/syntagmatic/tree.py
semiolog/syntagmatic/tokenizer/__init__ old.py
semiolog/syntagmatic/tokenizer/__init__.py
semiolog/syntagmatic/tokenizer/normalizers.py
semiolog/syntagmatic/tokenizer/post_processors.py
semiolog/syntagmatic/tokenizer/pre_tokenizers.py
semiolog/syntagmatic/tokenizer/processors.py
semiolog/syntagmatic/tokenizer/processors_old.py
semiolog/typing/__init__.py
semiolog/typing/ptype.py
semiolog-0.0.0.dist-info/LICENSE
semiolog-0.0.0.dist-info/METADATA
semiolog-0.0.0.dist-info/WHEEL
semiolog-0.0.0.dist-info/top_level.txt
semiolog-0.0.0.dist-info/RECORD
