Metadata-Version: 2.1
Name: semiolog
Version: 0.0.0
Summary: Tools for the semiological analysis of corpora
Home-page: https://gitlab.ethz.ch/semiomaths/semiolog
Author: Gianni Gastaldi
Author-email: Gianni Gastaldi <giannigastaldi@gmail.com>
License: Creative Commons Legal Code
Project-URL: Homepage, https://github.com/Gianni-G/semiolog
Keywords: texts,NLP,semiology,corpus,philosophy,semiomaths
Classifier: Development Status :: 3 - Alpha
Classifier: Intended Audience :: Science/Research
Classifier: Topic :: Text Processing :: Linguistic
Classifier: License :: CC0 1.0 Universal (CC0 1.0) Public Domain Dedication
Classifier: Programming Language :: Python :: 3.9
Requires-Python: >=3.9
License-File: LICENSE
Requires-Dist: typing
Requires-Dist: pathlib
Requires-Dist: datasets
Requires-Dist: tqdm
Requires-Dist: futures3
Requires-Dist: numpy
Requires-Dist: scipy
Requires-Dist: regex
Requires-Dist: networkx
Provides-Extra: dev
Requires-Dist: psutil ; extra == 'dev'
Requires-Dist: pyinstrument ; extra == 'dev'
Provides-Extra: full
Requires-Dist: ipywidgets ; extra == 'full'
Requires-Dist: iPython ; extra == 'full'
Requires-Dist: graphviz ; extra == 'full'
Requires-Dist: pandas ; extra == 'full'
Requires-Dist: nltk ; extra == 'full'
Requires-Dist: matplotlib ; extra == 'full'
Requires-Dist: seaborn ; extra == 'full'
Requires-Dist: plotly ; extra == 'full'
Requires-Dist: tokenizers ; extra == 'full'
Requires-Dist: transformers ; extra == 'full'
Requires-Dist: tensorflow ; extra == 'full'
